pyxedit/__init__.py
pyxedit/xedit/__init__.py
pyxedit/xedit/array.py
pyxedit/xedit/attribute.py
pyxedit/xedit/base.py
pyxedit/xedit/flags.py
pyxedit/xedit/generic.py
pyxedit/xedit/misc.py
pyxedit/xedit/plugin.py
pyxedit/xedit/xedit.py
pyxedit/xedit-lib/XEditLib.dll
pyxedit/xelib/__init__.py
pyxedit/xelib/definitions.py
pyxedit/xelib/xelib.py
pyxedit-0.1.1.dist-info/LICENSE
pyxedit-0.1.1.dist-info/METADATA
pyxedit-0.1.1.dist-info/WHEEL
pyxedit-0.1.1.dist-info/top_level.txt
pyxedit-0.1.1.dist-info/RECORD
