Metadata-Version: 2.1
Name: pyxedit
Version: 0.1.1
Summary: python wrapper around xedit-lib
Home-page: https://github.com/leontristain/pyxedit
Author: leontristain
License: UNKNOWN
Platform: UNKNOWN
Requires-Python: >=3.7
Requires-Dist: cached-property (>=1.5.1)
